datalake_sync/__init__.py
datalake_sync/connector.py
datalake_sync-0.1.0.dist-info/METADATA
datalake_sync-0.1.0.dist-info/WHEEL
datalake_sync-0.1.0.dist-info/top_level.txt
datalake_sync-0.1.0.dist-info/RECORD
